moving_targets/__init__.py
moving_targets/macs.py
moving_targets/callbacks/__init__.py
moving_targets/callbacks/callback.py
moving_targets/callbacks/console_logger.py
moving_targets/callbacks/data_logger.py
moving_targets/callbacks/file_logger.py
moving_targets/callbacks/history.py
moving_targets/callbacks/logger.py
moving_targets/callbacks/wandb_logger.py
moving_targets/learners/__init__.py
moving_targets/learners/curve_learners.py
moving_targets/learners/learner.py
moving_targets/learners/scikit_learners.py
moving_targets/learners/tensorflow_learners.py
moving_targets/learners/torch_learners.py
moving_targets/masters/__init__.py
moving_targets/masters/losses.py
moving_targets/masters/masters.py
moving_targets/masters/optimizers.py
moving_targets/masters/backends/__init__.py
moving_targets/masters/backends/backend.py
moving_targets/masters/backends/cplex_backend.py
moving_targets/masters/backends/cvxpy_backend.py
moving_targets/masters/backends/gurobi_backend.py
moving_targets/masters/backends/numpy_backend.py
moving_targets/metrics/__init__.py
moving_targets/metrics/classification.py
moving_targets/metrics/constraints.py
moving_targets/metrics/metric.py
moving_targets/metrics/regression.py
moving_targets/util/__init__.py
moving_targets/util/errors.py
moving_targets/util/masking.py
moving_targets/util/probabilities.py
moving_targets/util/scalers.py
moving_targets/util/typing.py
moving_targets-0.4.2.dist-info/METADATA
moving_targets-0.4.2.dist-info/WHEEL
moving_targets-0.4.2.dist-info/licenses/LICENSE
moving_targets-0.4.2.dist-info/RECORD
