Metadata-Version: 2.4
Name: moving-targets
Version: 0.4.2
Summary: Moving Targets: a framework for constrained machine learning
Project-URL: Repository, https://github.com/moving-targets/moving-targets/
Author: University of Bologna - DISI
Author-email: Luca Giuliani <luca.giuliani13@unibo.it>
Maintainer-email: Luca Giuliani <luca.giuliani13@unibo.it>
License-Expression: MIT
License-File: LICENSE
Classifier: Development Status :: 4 - Beta
Classifier: License :: OSI Approved :: MIT License
Classifier: Operating System :: OS Independent
Classifier: Programming Language :: Python
Requires-Python: >=3.8
Requires-Dist: matplotlib>=3.5
Requires-Dist: numpy>=1.24
Requires-Dist: pandas>=1.4
Requires-Dist: scikit-learn>=1.1
Provides-Extra: cplex
Requires-Dist: docplex>=2.23; extra == 'cplex'
Provides-Extra: cvxpy
Requires-Dist: cvxpy>=1.2; extra == 'cvxpy'
Provides-Extra: full
Requires-Dist: cvxpy>=1.2; extra == 'full'
Requires-Dist: docplex>=2.23; extra == 'full'
Requires-Dist: gurobipy>=9.5; extra == 'full'
Requires-Dist: tensorflow>=2.9; extra == 'full'
Requires-Dist: torch>=1.12; extra == 'full'
Requires-Dist: tqdm>=4.7.0; extra == 'full'
Requires-Dist: wandb>=0.13; extra == 'full'
Provides-Extra: gurobi
Requires-Dist: gurobipy>=9.5; extra == 'gurobi'
Provides-Extra: tensorflow
Requires-Dist: tensorflow>=2.9; extra == 'tensorflow'
Requires-Dist: wandb>=0.13; extra == 'tensorflow'
Provides-Extra: torch
Requires-Dist: torch>=1.12; extra == 'torch'
Requires-Dist: tqdm>=4.7.0; extra == 'torch'
Requires-Dist: wandb>=0.13; extra == 'torch'
